plexus/protobuf/setup/__init__.py
plexus_python_protobuf_setup-1.0.9.dist-info/METADATA
plexus_python_protobuf_setup-1.0.9.dist-info/WHEEL
plexus_python_protobuf_setup-1.0.9.dist-info/top_level.txt
plexus_python_protobuf_setup-1.0.9.dist-info/RECORD
